sink/__init__.py
sink/arch.py
sink/aur.py
sink/cli.py
sink/const.py
sink/logger.py
sink/package.py
sink-0.1.0b2.data/data/README.md
sink-0.1.0b2.dist-info/METADATA
sink-0.1.0b2.dist-info/WHEEL
sink-0.1.0b2.dist-info/entry_points.txt
sink-0.1.0b2.dist-info/top_level.txt
sink-0.1.0b2.dist-info/RECORD
